{
  "schema_version": "0.1",
  "review_name": "vol10_volume_entry_protocol_review",
  "phase": "Vol.10 Phase 10.0",
  "generated_at_sgt": "2026-06-18T00:00:00+08:00",
  "baseline": {
    "latest_completed_phase_before_phase": "Vol.9 Phase 9.10",
    "latest_commit_before_phase": "a183735f7afe68b768143d2455990cbea75c9056",
    "runtime_records_baseline_before_phase": 123,
    "vol9_status": "completed",
    "vol10_entry_readiness": "ready_with_limits",
    "customer_facing_readiness": false,
    "live_runtime_execution_frameworks": 0,
    "static_shell_mode": "local_static_read_only_fixture_only_no_network_no_execution"
  },
  "vol10_volume_entry_protocol_review_created": true,
  "volume_entry_checks": {
    "volume_milestone_plan": true,
    "principle_registry_review": true,
    "roadmap_alignment_review": true,
    "prior_volume_handoff_review": true,
    "scope_boundary_review": true,
    "forbidden_scope_review": true,
    "source_of_truth_review": true,
    "validation_plan": true,
    "open_questions_and_update_candidates": true
  },
  "principle_review": [
    {"principle_group": "first_principles_and_product_thesis", "drift_risk": "medium", "ambiguity": "Blueprint consolidation must remain product-thesis driven.", "update_candidate": "none", "entry_decision": "no_change"},
    {"principle_group": "duxd_real_scenario_feedback_loop", "drift_risk": "medium", "ambiguity": "DUXD feedback informs static planning only in this phase.", "update_candidate": "none", "entry_decision": "no_change"},
    {"principle_group": "human_strategy_ai_execution_boundary", "drift_risk": "high", "ambiguity": "Codex execution planning is not autonomous execution.", "update_candidate": "none", "entry_decision": "no_change"},
    {"principle_group": "source_of_truth_separation", "drift_risk": "high", "ambiguity": "TWOS runtime/product facts and LDD trading/execution facts remain separate.", "update_candidate": "none", "entry_decision": "no_change"},
    {"principle_group": "static_before_live_boundary", "drift_risk": "high", "ambiguity": "Static blueprint artifacts do not imply live readiness.", "update_candidate": "none", "entry_decision": "no_change"},
    {"principle_group": "no_live_implementation_without_gate", "drift_risk": "high", "ambiguity": "Planned Vol.10 phases do not activate future gates.", "update_candidate": "none", "entry_decision": "no_change"},
    {"principle_group": "customer_facing_readiness_false_until_gate", "drift_risk": "high", "ambiguity": "Customer-facing readiness stays false.", "update_candidate": "none", "entry_decision": "no_change"},
    {"principle_group": "memory_index_and_handoff_continuity", "drift_risk": "medium", "ambiguity": "Vol.10 entry artifacts need index visibility.", "update_candidate": "add_forward_references_only", "entry_decision": "no_principle_change"},
    {"principle_group": "volume_based_execution_and_handoff", "drift_risk": "medium", "ambiguity": "Vol.10 starts with entry review and must later close with exit review.", "update_candidate": "none", "entry_decision": "no_change"},
    {"principle_group": "roadmap_phase_vs_runtime_volume_taxonomy", "drift_risk": "high", "ambiguity": "Roadmap Phase 1/2 support must not be confused with runtime Vol.10.", "update_candidate": "none", "entry_decision": "no_change"}
  ],
  "principle_update_decisions": [
    {"principle_group": "first_principles_and_product_thesis", "decision": "no_change"},
    {"principle_group": "duxd_real_scenario_feedback_loop", "decision": "no_change"},
    {"principle_group": "human_strategy_ai_execution_boundary", "decision": "no_change"},
    {"principle_group": "source_of_truth_separation", "decision": "no_change"},
    {"principle_group": "static_before_live_boundary", "decision": "no_change"},
    {"principle_group": "no_live_implementation_without_gate", "decision": "no_change"},
    {"principle_group": "customer_facing_readiness_false_until_gate", "decision": "no_change"},
    {"principle_group": "memory_index_and_handoff_continuity", "decision": "no_principle_change_forward_references_only"},
    {"principle_group": "volume_based_execution_and_handoff", "decision": "no_change"},
    {"principle_group": "roadmap_phase_vs_runtime_volume_taxonomy", "decision": "no_change"}
  ],
  "roadmap_alignment_review": {
    "supports_roadmap_phase_1_static_blueprint": true,
    "supports_roadmap_phase_2_manual_prototype_validation": true,
    "roadmap_phase_3_mvp_build_activated": false,
    "roadmap_phase_4_multi_model_execution_layer_activated": false,
    "roadmap_phase_5_ecosystem_public_collaboration_activated": false,
    "taxonomy_layers_distinct": true
  },
  "source_of_truth_review": {
    "twos_runtime_product_sot_must_never_override_ldd_trading_execution_sot": true,
    "ldd_trading_execution_sot_must_never_override_twos_runtime_product_sot": true,
    "product_runtime_records_override_trading_facts": false,
    "ldd_trading_facts_imply_product_readiness": false,
    "quote_type_boundaries_preserved_as_future_static_requirements_only": true,
    "execution_evidence_boundaries_preserved_as_future_static_requirements_only": true
  },
  "forbidden_scope_review": {
    "all_forbidden_scope_blocked": true,
    "production_ui": false,
    "customer_facing_ui": false,
    "hosted_app": false,
    "api_server": false,
    "live_endpoint": false,
    "external_api": false,
    "broker_connection": false,
    "binance_connection": false,
    "live_market_data": false,
    "trading_automation": false,
    "credential_handling": false,
    "login_auth": false,
    "runtime_mutation": false,
    "execution_trigger": false,
    "order_placement": false,
    "portfolio_modification": false,
    "background_worker": false,
    "scheduler": false,
    "notification_dispatcher": false,
    "github_issues": false,
    "github_projects_board": false,
    "package_manager_files": false,
    "build_tools": false,
    "frontend_framework": false,
    "network_dependency": false,
    "external_integration": false,
    "production_deployment_capability": false
  },
  "quote_type_preservation": [
    "watchlist_price",
    "premarket_price",
    "holding_valuation_price",
    "order_page_executable_price",
    "final_filled_price"
  ],
  "execution_evidence_boundaries": [
    "actual_filled_trade",
    "expired_zero_fill_order",
    "canceled_order",
    "portfolio_change",
    "no_cash_impact_event"
  ],
  "validation_plan": {
    "required_commands": [
      "bash scripts/validate_runtime_records.sh",
      "bash scripts/validate_vol10_phase10_0_entry_protocol.sh",
      "bash scripts/validate_vol9_phase9_10_handoff_and_vol10_readiness.sh"
    ],
    "baseline_commit_reference_required": true,
    "runtime_records_baseline_123_required": true,
    "phase10_1_not_started_required": true,
    "customer_facing_readiness_false_required": true,
    "live_runtime_execution_capability_false_required": true
  },
  "phase10_1_started": false,
  "customer_facing_readiness": false,
  "live_runtime_execution_frameworks": 0,
  "live_runtime_execution_capability": false,
  "future_gate_activation": false,
  "static_shell_mode": "local_static_read_only_fixture_only_no_network_no_execution",
  "trading_facts_changed": false,
  "portfolio_state_changed": false,
  "execution_ledger_changed": false,
  "cash_state_changed": false,
  "broker_connection_changed": false,
  "binance_connection_changed": false,
  "acceptance": {
    "vol10_volume_entry_protocol_review_created": true,
    "all_required_entry_checks_present": true,
    "phase10_1_started": false,
    "customer_facing_readiness": false,
    "live_runtime_execution_capability": false
  }
}
